setup.cfg
setup.py
bin/qi
git_qi.egg-info/PKG-INFO
git_qi.egg-info/SOURCES.txt
git_qi.egg-info/dependency_links.txt
git_qi.egg-info/requires.txt
git_qi.egg-info/top_level.txt
qi/Arguments.py
qi/GitClient.py
qi/TimeIterators.py
qi/__init__.py