Metadata-Version: 1.1
Name: git-qi
Version: 0.2.1
Summary: Qi prints Git revisions in structured time intervals for later analysis.
Home-page: UNKNOWN
Author: Sage Gerard
Author-email: sage@sagegerard.com
License: MIT
Download-URL: https://github.com/zyrolasting/qi/archive/v0.2.1.tar.gz
Keywords: git,commit,history,analysis
Platform: UNKNOWN
